{
	"name": "BidUnit",
	"properties": {
		"linkedServiceName": {
			"referenceName": "DashboardDb",
			"type": "LinkedServiceReference"
		},
		"folder": {
			"name": "Twitter"
		},
		"annotations": [],
		"type": "AzureSqlTable",
		"schema": [
			{
				"name": "Id",
				"type": "smallint",
				"precision": 5
			},
			{
				"name": "Name",
				"type": "varchar"
			},
			{
				"name": "DisplayName",
				"type": "varchar"
			}
		],
		"typeProperties": {
			"schema": "dbo",
			"table": "BidUnit"
		}
	},
	"type": "Microsoft.DataFactory/factories/datasets"
}